ahcm.py
mglob.py
path.py
setup.py
ahcm.egg-info/PKG-INFO
ahcm.egg-info/SOURCES.txt
ahcm.egg-info/dependency_links.txt
ahcm.egg-info/entry_points.txt
ahcm.egg-info/top_level.txt
