Metadata-Version: 1.0
Name: ahcm
Version: 0.1
Summary: ahcm - ad hoc configuration management tool
Home-page: http://vvtools.googlecode.com/svn/trunk/ahcm#egg=ahcm-dev
Author: Ville M. Vainio
Author-email: vivainio@gmail.com
License: UNKNOWN
Platform: UNKNOWN
